futureexpert/__about__.py
futureexpert/__init__.py
futureexpert/_forecast_consistency_metadata.py
futureexpert/_future_api.py
futureexpert/_helpers.py
futureexpert/associator.py
futureexpert/checkin.py
futureexpert/expert_client.py
futureexpert/forecast.py
futureexpert/forecast_consistency.py
futureexpert/matcher.py
futureexpert/plot.py
futureexpert/pool.py
futureexpert/py.typed
futureexpert/shared_models.py
futureexpert-2.2.0.dist-info/licenses/LICENSE
futureexpert-2.2.0.dist-info/METADATA
futureexpert-2.2.0.dist-info/WHEEL
futureexpert-2.2.0.dist-info/top_level.txt
futureexpert-2.2.0.dist-info/RECORD
