Metadata-Version: 2.4
Name: futureexpert
Version: 2.2.0
Summary: Forecasting has never been easier.
Author-email: prognostica GmbH <support@future-forecasting.de>
License: MIT
Project-URL: homepage, https://www.future-forecasting.de
Project-URL: source, https://github.com/discovertomorrow/futureexpert
Project-URL: tracker, https://github.com/discovertomorrow/futureexpert/issues
Project-URL: release notes, https://github.com/discovertomorrow/futureEXPERT/releases
Keywords: time-series,forecast,ml
Classifier: License :: OSI Approved :: MIT License
Classifier: Programming Language :: Python :: 3
Classifier: Programming Language :: Python :: 3.9
Classifier: Programming Language :: Python :: 3.10
Classifier: Programming Language :: Python :: 3.11
Classifier: Programming Language :: Python :: 3.12
Classifier: Programming Language :: Python :: 3 :: Only
Classifier: Intended Audience :: Developers
Classifier: Intended Audience :: Science/Research
Classifier: Topic :: Scientific/Engineering
Classifier: Topic :: Software Development
Classifier: Typing :: Typed
Requires-Python: >=3.9
License-File: LICENSE
Requires-Dist: python-keycloak==3.12.0
Requires-Dist: tenacity>=8.2.0
Requires-Dist: httpx>=0.27.2
Requires-Dist: matplotlib>=3.8.0
Requires-Dist: plotly>=5.24.1
Requires-Dist: pydantic<3.0.0,>=2.5.0
Requires-Dist: numpy<2.0.0,>=1.22.4
Requires-Dist: pandas>=1.4.3
Requires-Dist: python-dotenv
Provides-Extra: dev
Requires-Dist: pytest; extra == "dev"
Requires-Dist: ipytest; extra == "dev"
Requires-Dist: isort; extra == "dev"
Requires-Dist: mypy==1.0.*; extra == "dev"
Requires-Dist: autopep8; extra == "dev"
Requires-Dist: cloudpickle; extra == "dev"
Requires-Dist: pdoc3; extra == "dev"
Requires-Dist: types-pkg-resources==0.1.3; extra == "dev"
Requires-Dist: types-python-dateutil; extra == "dev"
Requires-Dist: types-toml; extra == "dev"
Requires-Dist: jupyter==1.0.0; extra == "dev"
Requires-Dist: nbconvert==7.2.6; extra == "dev"
Requires-Dist: nbqa==1.5.3; extra == "dev"
Requires-Dist: python-dotenv; extra == "dev"
Requires-Dist: lxml; extra == "dev"
Dynamic: license-file
